akeneo_api_client_globus/akeneo_api_client.py
akeneo_api_client_globus/akeneo_api_client_utils.py
akeneo_api_client_globus-0.0.3.dist-info/LICENSE
akeneo_api_client_globus-0.0.3.dist-info/METADATA
akeneo_api_client_globus-0.0.3.dist-info/WHEEL
akeneo_api_client_globus-0.0.3.dist-info/top_level.txt
akeneo_api_client_globus-0.0.3.dist-info/RECORD
