Metadata-Version: 2.1
Name: akeneo_api_client_globus
Version: 0.0.3
Summary: API Client for Akeneo
Author-email: MDM <mdm@globus.ch>
Project-URL: Homepage, https://github.com/pypa/sampleproject
Project-URL: Bug Tracker, https://github.com/pypa/sampleproject/issues
Classifier: Programming Language :: Python :: 3
Classifier: License :: OSI Approved :: MIT License
Classifier: Operating System :: OS Independent
Requires-Python: >=3.7
License-File: LICENSE
